django_kerberos/__init__.py
django_kerberos/app_settings.py
django_kerberos/backends.py
django_kerberos/hashers.py
django_kerberos/models.py
django_kerberos/urls.py
django_kerberos/views.py
django_kerberos/static/js/autologin.js
django_kerberos/templates/django_kerberos/autologin.html
django_kerberos/templates/django_kerberos/base.html
django_kerberos/templates/django_kerberos/error.html
django_kerberos/templates/django_kerberos/unauthorized.html
django_kerberos-1.4.4.dist-info/COPYING
django_kerberos-1.4.4.dist-info/METADATA
django_kerberos-1.4.4.dist-info/WHEEL
django_kerberos-1.4.4.dist-info/top_level.txt
django_kerberos-1.4.4.dist-info/RECORD
