Metadata-Version: 2.1
Name: django-kerberos
Version: 1.4.4
Summary: Kerberos authentication for Django
Home-page: http://dev.entrouvert.org/projects/authentic/
Author: Entr'ouvert
Author-email: info@entrouvert.org
Maintainer: Benjamin Dauvergne
Maintainer-email: bdauvergne@entrouvert.com
License: AGPLv3 or later
Platform: UNKNOWN
Requires-Dist: six
Requires-Dist: django (>1.8)
Requires-Dist: pykerberos
